{"cameraMode":{"drawMode":0,"name":"Shaded","section":"Shading Mode"},"sceneLighting":false,"audioPlay":false,"sceneViewState":{"m_AlwaysRefresh":true,"showFog":true,"showSkybox":true,"showFlares":true,"showImageEffects":true,"showParticleSystems":true,"showVisualEffectGraphs":true,"m_FxEnabled":true},"in2DMode":false,"pivot":{"x":-546.71875,"y":-732.3857421875,"z":2144.000244140625},"rotation":{"x":-0.30112066864967348,"y":0.40024325251579287,"z":-0.14114177227020265,"w":-0.8539860248565674},"size":1347.06201171875,"orthographic":false}