{"cameraMode":{"drawMode":0,"name":"Shaded","section":"Shading Mode"},"sceneLighting":false,"audioPlay":false,"sceneViewState":{"m_AlwaysRefresh":true,"showFog":true,"showSkybox":true,"showFlares":true,"showImageEffects":true,"showParticleSystems":true,"showVisualEffectGraphs":true,"m_FxEnabled":true},"in2DMode":false,"pivot":{"x":-3976.1103515625,"y":-1095.926025390625,"z":2828.713134765625},"rotation":{"x":-0.36798208951950076,"y":0.6214052438735962,"z":-0.4110698997974396,"w":-0.5563527941703796},"size":658.0276489257813,"orthographic":false}